jobcreator/__init__.py
jobcreator/__main__.py
jobcreator/_version.py
jobcreator/_job_templates/__init__.py
jobcreator/_job_templates/caiman/__init__.py
jobcreator/_job_templates/caiman/caiman_mcorr_template.py
jobcreator/_job_templates/caiman/caiman_template.py
jobcreator/_job_templates/suite2p/__init__.py
jobcreator/_job_templates/suite2p/suite2p_template.py
jobcreator/_pipeline_checks/__init__.py
jobcreator/_pipeline_checks/check_caiman.py
jobcreator/_pipeline_runners/__init__.py
jobcreator/_pipeline_runners/caiman/__init__.py
jobcreator/_pipeline_runners/caiman/caiman_constants.py
jobcreator/_pipeline_runners/caiman/caiman_desktop_runner.py
jobcreator/_pipeline_runners/caiman/caiman_mcorr.py
jobcreator/_pipeline_runners/caiman/caiman_runner.py
jobcreator/_pipeline_runners/suite2p/__init__.py
jobcreator/_pipeline_runners/suite2p/suite2p_runner.py
jobcreator/utils/__init__.py
jobcreator/utils/misc.py
jobcreator-0.0.11.dist-info/LICENSE
jobcreator-0.0.11.dist-info/METADATA
jobcreator-0.0.11.dist-info/WHEEL
jobcreator-0.0.11.dist-info/entry_points.txt
jobcreator-0.0.11.dist-info/top_level.txt
jobcreator-0.0.11.dist-info/RECORD
