Metadata-Version: 2.1
Name: jobcreator
Version: 0.0.11
Summary: CLI for setting up and running slurm jobs
Home-page: https://github.com/donatolab/jobcreator
Author: UNKNOWN
Author-email: UNKNOWN
License: GPL
Platform: UNKNOWN
Requires-Dist: h5py
Requires-Dist: numpy
